Metadata-Version: 1.1
Name: bayrell-parser
Version: 0.0.1
Summary: Bayrell Parser
Home-page: https://github.com/bayrell/parser_py3
Author: Ildar Bikmamatov
Author-email: ildar@bayrell.org
License: Apache License Version 2.0
Platform: UNKNOWN
Classifier: Development Status :: 1 - Planning
Classifier: Environment :: Console
Classifier: Environment :: Web Environment
Classifier: Intended Audience :: Developers
Classifier: License :: OSI Approved :: Apache Software License
Classifier: Operating System :: OS Independent
Classifier: Programming Language :: Python
Classifier: Programming Language :: Python :: 3.5
Classifier: Topic :: Internet
Classifier: Topic :: Software Development :: Interpreters
Classifier: Topic :: Software Development :: Libraries
